mp4_to_gif/__init__.py
mp4_to_gif/cli.py
mp4_to_gif/converter.py
mp4_to_gif_cli-1.1.0.dist-info/METADATA
mp4_to_gif_cli-1.1.0.dist-info/WHEEL
mp4_to_gif_cli-1.1.0.dist-info/entry_points.txt
mp4_to_gif_cli-1.1.0.dist-info/top_level.txt
mp4_to_gif_cli-1.1.0.dist-info/RECORD
